donkeycar/__init__.py
donkeycar/config.py
donkeycar/geom.py
donkeycar/la.py
donkeycar/memory.py
donkeycar/utils.py
donkeycar/vehicle.py
donkeycar/benchmarks/tub.py
donkeycar/benchmarks/tub_v2.py
donkeycar/contrib/__init__.py
donkeycar/contrib/robohat/code-robocarstore.py
donkeycar/contrib/robohat/code.py
donkeycar/contrib/robohat/rear_light.py
donkeycar/gym/__init__.py
donkeycar/gym/gym_real.py
donkeycar/gym/remote_controller.py
donkeycar/management/__init__.py
donkeycar/management/base.py
donkeycar/management/graph.py
donkeycar/management/joystick_creator.py
donkeycar/management/kivy_ui.py
donkeycar/management/makemovie.py
donkeycar/management/tub.py
donkeycar/parts/__init__.py
donkeycar/parts/actuator.py
donkeycar/parts/behavior.py
donkeycar/parts/camera.py
donkeycar/parts/controller.py
donkeycar/parts/coral.py
donkeycar/parts/cv.py
donkeycar/parts/datastore.py
donkeycar/parts/datastore_v2.py
donkeycar/parts/dgym.py
donkeycar/parts/encoder.py
donkeycar/parts/fast_stretch.py
donkeycar/parts/fastai.py
donkeycar/parts/file_watcher.py
donkeycar/parts/fps.py
donkeycar/parts/graph.py
donkeycar/parts/image.py
donkeycar/parts/imu.py
donkeycar/parts/interpreter.py
donkeycar/parts/keras.py
donkeycar/parts/launch.py
donkeycar/parts/led_status.py
donkeycar/parts/leopard_imaging.py
donkeycar/parts/lidar.py
donkeycar/parts/network.py
donkeycar/parts/oled.py
donkeycar/parts/path.py
donkeycar/parts/perfmon.py
donkeycar/parts/pigpio_enc.py
donkeycar/parts/realsense2.py
donkeycar/parts/realsense435i.py
donkeycar/parts/robohat.py
donkeycar/parts/ros.py
donkeycar/parts/salient.py
donkeycar/parts/serial_controller.py
donkeycar/parts/simulation.py
donkeycar/parts/sombrero.py
donkeycar/parts/teensy.py
donkeycar/parts/telemetry.py
donkeycar/parts/throttle_filter.py
donkeycar/parts/transform.py
donkeycar/parts/tub_v2.py
donkeycar/parts/object_detector/stop_sign_detector.py
donkeycar/parts/pytorch/ResNet18.py
donkeycar/parts/pytorch/torch_data.py
donkeycar/parts/pytorch/torch_train.py
aicoe_donkeycar-4.3.0.post1.dist-info/LICENSE
aicoe_donkeycar-4.3.0.post1.dist-info/METADATA
aicoe_donkeycar-4.3.0.post1.dist-info/WHEEL
aicoe_donkeycar-4.3.0.post1.dist-info/entry_points.txt
aicoe_donkeycar-4.3.0.post1.dist-info/top_level.txt
aicoe_donkeycar-4.3.0.post1.dist-info/RECORD
