Metadata-Version: 2.1
Name: aicoe-donkeycar
Version: 4.3.0.post1
Summary: Self driving library for python.
Home-page: https://github.com/autorope/donkeycar
Author: Will Roscoe, Adam Conway, Tawn Kramer
Author-email: wroscoe@gmail.com, adam@casaconway.com, tawnkramer@gmail.com
License: MIT
Keywords: selfdriving cars donkeycar diyrobocars
Platform: UNKNOWN
Classifier: Development Status :: 4 - Beta
Classifier: Intended Audience :: Developers
Classifier: Topic :: Scientific/Engineering :: Artificial Intelligence
Classifier: License :: OSI Approved :: MIT License
Classifier: Programming Language :: Python :: 3.6
Classifier: Programming Language :: Python :: 3.7
License-File: LICENSE
Requires-Dist: numpy
Requires-Dist: pillow
Requires-Dist: docopt
Requires-Dist: tornado
Requires-Dist: requests
Requires-Dist: h5py
Requires-Dist: PrettyTable
Requires-Dist: paho-mqtt
Requires-Dist: simple-pid
Requires-Dist: progress
Requires-Dist: typing-extensions
Requires-Dist: pyfiglet
Requires-Dist: psutil
Provides-Extra: ci
Requires-Dist: codecov ; extra == 'ci'
Provides-Extra: dev
Requires-Dist: pytest ; extra == 'dev'
Requires-Dist: pytest-cov ; extra == 'dev'
Requires-Dist: responses ; extra == 'dev'
Requires-Dist: mypy ; extra == 'dev'
Provides-Extra: mm1
Requires-Dist: pyserial ; extra == 'mm1'
Provides-Extra: nano
Requires-Dist: Adafruit-PCA9685 ; extra == 'nano'
Requires-Dist: adafruit-circuitpython-lis3dh ; extra == 'nano'
Requires-Dist: adafruit-circuitpython-ssd1306 ; extra == 'nano'
Requires-Dist: RPi.GPIO ; extra == 'nano'
Provides-Extra: pc
Requires-Dist: matplotlib ; extra == 'pc'
Requires-Dist: imgaug ; extra == 'pc'
Requires-Dist: kivy ; extra == 'pc'
Provides-Extra: pi
Requires-Dist: picamera ; extra == 'pi'
Requires-Dist: Adafruit-PCA9685 ; extra == 'pi'
Requires-Dist: adafruit-circuitpython-lis3dh ; extra == 'pi'
Requires-Dist: adafruit-circuitpython-ssd1306 ; extra == 'pi'
Requires-Dist: RPi.GPIO ; extra == 'pi'
Requires-Dist: pyserial ; extra == 'pi'
Provides-Extra: tf
Requires-Dist: tensorflow (==2.2.0) ; extra == 'tf'
Provides-Extra: torch
Requires-Dist: pytorch (>=1.7.1) ; extra == 'torch'
Requires-Dist: torchvision ; extra == 'torch'
Requires-Dist: torchaudio ; extra == 'torch'
